odoo/addons/mrp_2_steps_consumed_qty_sync/README.rst
odoo/addons/mrp_2_steps_consumed_qty_sync/__init__.py
odoo/addons/mrp_2_steps_consumed_qty_sync/__manifest__.py
odoo/addons/mrp_2_steps_consumed_qty_sync/i18n/es.po
odoo/addons/mrp_2_steps_consumed_qty_sync/i18n/mrp_2_steps_consumed_qty_sync.pot
odoo/addons/mrp_2_steps_consumed_qty_sync/models/__init__.py
odoo/addons/mrp_2_steps_consumed_qty_sync/models/stock_picking.py
odoo/addons/mrp_2_steps_consumed_qty_sync/readme/CONTRIBUTORS.rst
odoo/addons/mrp_2_steps_consumed_qty_sync/readme/DESCRIPTION.rst
odoo/addons/mrp_2_steps_consumed_qty_sync/static/description/icon.png
odoo/addons/mrp_2_steps_consumed_qty_sync/static/description/index.html
odoo/addons/mrp_2_steps_consumed_qty_sync/tests/__init__.py
odoo/addons/mrp_2_steps_consumed_qty_sync/tests/test_mrp_2_steps_consumed_qty_sync.py
odoo_addon_mrp_2_steps_consumed_qty_sync-15.0.0.1.0.2.dist-info/METADATA
odoo_addon_mrp_2_steps_consumed_qty_sync-15.0.0.1.0.2.dist-info/WHEEL
odoo_addon_mrp_2_steps_consumed_qty_sync-15.0.0.1.0.2.dist-info/top_level.txt
odoo_addon_mrp_2_steps_consumed_qty_sync-15.0.0.1.0.2.dist-info/RECORD
